PokeAppUtils/__init__.py
PokeAppUtils/datas.py
PokeAppUtils/teamSynergies.py
PokeAppUtils-0.0.2.dist-info/METADATA
PokeAppUtils-0.0.2.dist-info/WHEEL
PokeAppUtils-0.0.2.dist-info/top_level.txt
PokeAppUtils-0.0.2.dist-info/RECORD
